LICENSE
MANIFEST.in
README.rst
setup.py
django_html_sweatshop.egg-info/PKG-INFO
django_html_sweatshop.egg-info/SOURCES.txt
django_html_sweatshop.egg-info/dependency_links.txt
django_html_sweatshop.egg-info/not-zip-safe
django_html_sweatshop.egg-info/requires.txt
django_html_sweatshop.egg-info/top_level.txt
html_sweatshop/__init__.py
html_sweatshop/admin.py
html_sweatshop/conf.py
html_sweatshop/models.py
html_sweatshop/tests.py
html_sweatshop/views.py
html_sweatshop/locale/en/LC_MESSAGES/django.mo
html_sweatshop/locale/en/LC_MESSAGES/django.po
html_sweatshop/static/one_step_delete/js/init_one_step_delete.js
html_sweatshop/static/one_step_delete/js/themes/bootstrap3/jquery.one-step-delete.js
html_sweatshop/templates/digg_pagination/digg_paginator.html
html_sweatshop/templates/digg_pagination/themes/bootstrap3.html
html_sweatshop/templates/django_tables2/paginated_table.html
html_sweatshop/templates/django_tables2/themes/bootstrap3.html
html_sweatshop/templates/message_centre/messages.html
html_sweatshop/templates/message_centre/themes/bootstrap3.html
html_sweatshop/templates/one_step_delete/delete_confirm_dialog.html
html_sweatshop/templates/one_step_delete/include_js.html
html_sweatshop/templates/one_step_delete/themes/bootstrap3.html
html_sweatshop/templatetags/__init__.py
html_sweatshop/templatetags/digg_pagination_tags.py
html_sweatshop/templatetags/message_centre_tags.py
html_sweatshop/templatetags/one_step_delete_tags.py