Metadata-Version: 1.1
Name: django-html-sweatshop
Version: 0.1.0
Summary: A Django app that simplifies some common HTML rendering
Home-page: https://github.com/georgema1982/django-html-sweatshop
Author: George Ma
Author-email: george.ma1982@gmail.com
License: MIT
Platform: UNKNOWN
Classifier: Development Status :: 3 - Alpha
Classifier: Framework :: Django
Classifier: Intended Audience :: Developers
Classifier: License :: OSI Approved :: MIT License
Classifier: Operating System :: OS Independent
Classifier: Programming Language :: Python
Classifier: Topic :: Internet :: WWW/HTTP
